[
  {
    "id": "47665137-e423-4e87-b419-edebf802cda6",
    "title": "n8n approved post 5:32:43 AM",
    "platform": "Instagram",
    "owner": "Automation",
    "stage": "scheduled",
    "status": "Approved via n8n",
    "due": "2026-04-09T16:32:43.236Z",
    "notes": "This item was inserted by the webhook demo button.",
    "source": "n8n",
    "createdAt": "2026-04-08T04:32:43.245Z",
    "updatedAt": "2026-04-08T04:32:43.245Z"
  },
  {
    "id": "planner-001",
    "title": "Easter reflection carousel",
    "platform": "General",
    "owner": "Team",
    "stage": "scheduled",
    "status": "Scheduled",
    "due": "2026-04-08T18:00",
    "notes": "Scripture-based carousel for evening engagement.",
    "source": "manual-edit",
    "createdAt": "2026-04-08T08:00:00.000Z",
    "updatedAt": "2026-04-08T04:34:27.033Z"
  },
  {
    "id": "planner-002",
    "title": "Student success story short",
    "platform": "TikTok",
    "owner": "Media",
    "stage": "ideas",
    "status": "Research",
    "due": "2026-04-09T12:00:00",
    "notes": "Feature a BYU-Pathway transformation story.",
    "source": "manual",
    "createdAt": "2026-04-08T08:05:00.000Z",
    "updatedAt": "2026-04-08T08:05:00.000Z"
  },
  {
    "id": "planner-003",
    "title": "Pathway motivation reel",
    "platform": "General",
    "owner": "Team",
    "stage": "scheduled",
    "status": "Scheduled",
    "due": "2026-04-10T18:30:00",
    "notes": "Need captions and brand outro.",
    "source": "manual-edit",
    "createdAt": "2026-04-08T08:10:00.000Z",
    "updatedAt": "2026-04-08T04:34:29.007Z"
  },
  {
    "id": "planner-004",
    "title": "Weekly devotional thread",
    "platform": "X",
    "owner": "Comms",
    "stage": "production",
    "status": "Awaiting Approval",
    "due": "2026-04-11T10:00:00",
    "notes": "Need final approval from content lead.",
    "source": "manual",
    "createdAt": "2026-04-08T08:15:00.000Z",
    "updatedAt": "2026-04-08T08:15:00.000Z"
  },
  {
    "id": "planner-005",
    "title": "Sunday worship reminder",
    "platform": "Facebook",
    "owner": "Team",
    "stage": "scheduled",
    "status": "Scheduled",
    "due": "2026-04-12T19:00:00",
    "notes": "Publish before the Sunday livestream.",
    "source": "n8n",
    "createdAt": "2026-04-08T08:20:00.000Z",
    "updatedAt": "2026-04-08T08:20:00.000Z"
  }
]